3108-Computer Architecture/Lab Final(29-06-2025)/HDL/4-bit down counter/subone.v
module subone (
    input wire [3:0]I,
    output wire [3:0]O
);

assign O=I-1;
    
endmodule

3108-Computer Architecture/Lab Final(29-06-2025)/HDL/4-bit down counter/register.v
module register (
    input wire [3:0]d,
    input wire clk,
    input wire reset,
    output wire [3:0]q
);

reg [3:0]r_reg;
wire [3:0]r_next;

always @(posedge clk, posedge reset) 
begin
    if (reset)
        r_reg<=4'b0000;
    else
        r_reg<=r_next;
end

assign r_next=d;    
assign q=r_reg;

endmodule

3108-Computer Architecture/Lab Final(29-06-2025)/HDL/4-bit down counter/counter.v
module counter (
    input wire clk,
    input wire reset,
    output wire [3:0]q
);

wire [3:0]d_temp,q_temp;

register c1(d_temp,clk,reset,q_temp);
subone c2(q_temp,d_temp);

assign q=q_temp;
    
endmodule

3108-Computer Architecture/Lab Final(29-06-2025)/HDL/4-bit down counter/cnt_tb.v
`timescale 1ns/1ps
module cnt_tb;
reg clk;
reg reset;
wire [3:0]q;

counter uut(clk,reset,q);

always begin
    clk=~clk;
    #10;    
end

initial begin
    $dumpfile("test.vcd");
    $dumpvars(0,cnt_tb);

    clk<=0;
    reset<=1;
    #20;
    reset<=0;
    #20;#20;#20;#20;#20;#20;#20;#20;#20;#20;#20;#20;#20;
    #40;

    $finish;

end

initial begin
    $monitor("reset=%b clk=%b q=%b",reset,clk,q);
end
    
endmodule

3108-Computer Architecture/Lab Final(29-06-2025)/HDL/4-bit down counter/test.vcd
$date
	Thu Jul 03 16:18:50 2025
$end
$version
	Icarus Verilog
$end
$timescale
	1ps
$end
$scope module cnt_tb $end
$var wire 4 ! q [3:0] $end
$var reg 1 " clk $end
$var reg 1 # reset $end
$scope module uut $end
$var wire 1 " clk $end
$var wire 4 $ q [3:0] $end
$var wire 1 # reset $end
$var wire 4 % q_temp [3:0] $end
$var wire 4 & d_temp [3:0] $end
$scope module c1 $end
$var wire 1 " clk $end
$var wire 4 ' r_next [3:0] $end
$var wire 1 # reset $end
$var wire 4 ( q [3:0] $end
$var wire 4 ) d [3:0] $end
$var reg 4 * r_reg [3:0] $end
$upscope $end
$scope module c2 $end
$var wire 4 + I [3:0] $end
$var wire 4 , O [3:0] $end
$upscope $end
$upscope $end
$upscope $end
$enddefinitions $end
$comment Show the parameter values. $end
$dumpall
$end
#0
$dumpvars
b1111 ,
b0 +
b0 *
b1111 )
b0 (
b1111 '
b1111 &
b0 %
b0 $
1#
0"
b0 !
$end
#10000
1"
#20000
0#
0"
#30000
b1110 '
b1110 &
b1110 )
b1110 ,
b1111 !
b1111 $
b1111 %
b1111 (
b1111 *
b1111 +
1"
#40000
0"
#50000
b1101 '
b1101 &
b1101 )
b1101 ,
b1110 !
b1110 $
b1110 %
b1110 (
b1110 *
b1110 +
1"
#60000
0"
#70000
b1100 '
b1100 &
b1100 )
b1100 ,
b1101 !
b1101 $
b1101 %
b1101 (
b1101 *
b1101 +
1"
#80000
0"
#90000
b1011 '
b1011 &
b1011 )
b1011 ,
b1100 !
b1100 $
b1100 %
b1100 (
b1100 *
b1100 +
1"
#100000
0"
#110000
b1010 '
b1010 &
b1010 )
b1010 ,
b1011 !
b1011 $
b1011 %
b1011 (
b1011 *
b1011 +
1"
#120000
0"
#130000
b1001 '
b1001 &
b1001 )
b1001 ,
b1010 !
b1010 $
b1010 %
b1010 (
b1010 *
b1010 +
1"
#140000
0"
#150000
b1000 '
b1000 &
b1000 )
b1000 ,
b1001 !
b1001 $
b1001 %
b1001 (
b1001 *
b1001 +
1"
#160000
0"
#170000
b111 '
b111 &
b111 )
b111 ,
b1000 !
b1000 $
b1000 %
b1000 (
b1000 *
b1000 +
1"
#180000
0"
#190000
b110 '
b110 &
b110 )
b110 ,
b111 !
b111 $
b111 %
b111 (
b111 *
b111 +
1"
#200000
0"
#210000
b101 '
b101 &
b101 )
b101 ,
b110 !
b110 $
b110 %
b110 (
b110 *
b110 +
1"
#220000
0"
#230000
b100 '
b100 &
b100 )
b100 ,
b101 !
b101 $
b101 %
b101 (
b101 *
b101 +
1"
#240000
0"
#250000
b11 '
b11 &
b11 )
b11 ,
b100 !
b100 $
b100 %
b100 (
b100 *
b100 +
1"
#260000
0"
#270000
b10 '
b10 &
b10 )
b10 ,
b11 !
b11 $
b11 %
b11 (
b11 *
b11 +
1"
#280000
0"
#290000
b1 '
b1 &
b1 )
b1 ,
b10 !
b10 $
b10 %
b10 (
b10 *
b10 +
1"
#300000
0"
#310000
b0 '
b0 &
b0 )
b0 ,
b1 !
b1 $
b1 %
b1 (
b1 *
b1 +
1"
